tracy_nn/__init__.py
tracy_nn-0.1.0.dist-info/licenses/LICENSE
tracy_nn-0.1.0.dist-info/METADATA
tracy_nn-0.1.0.dist-info/WHEEL
tracy_nn-0.1.0.dist-info/top_level.txt
tracy_nn-0.1.0.dist-info/RECORD
