Metadata-Version: 2.4
Name: tracy-nn
Version: 0.1.0
Summary: A lightweight tracer for understanding & debugging PyTorch neural networks
Author-email: Billy Pu$h3r <billypush3r@proton.me>
License: MIT License
Project-URL: Homepage, https://itsalirezajalouli.github.io/posts/tracy-nn-doc/
Requires-Python: >=3.8
License-File: LICENSE
Requires-Dist: torch
Dynamic: license-file
